vvifi/__init__.py
vvifi/cli.py
vvifi/constants.py
vvifi/utils.py
vvifi-0.1.0.dist-info/entry_points.txt
vvifi-0.1.0.dist-info/LICENSE
vvifi-0.1.0.dist-info/WHEEL
vvifi-0.1.0.dist-info/METADATA
vvifi-0.1.0.dist-info/RECORD
