Metadata-Version: 2.1
Name: vvifi
Version: 0.1.0
Summary: A Python CLI to quickly check your Wi-Fi network password.
Home-page: https://github.com/joaopalmeiro/vvifi
License: MIT
Keywords: vvifi,cli,wifi,password
Author: João Palmeiro
Author-email: joaommpalmeiro@gmail.com
Requires-Python: >=3.6,<4.0
Classifier: Development Status :: 3 - Alpha
Classifier: Environment :: Console
Classifier: Intended Audience :: Developers
Classifier: Intended Audience :: Information Technology
Classifier: Intended Audience :: Science/Research
Classifier: License :: OSI Approved :: MIT License
Classifier: Natural Language :: English
Classifier: Operating System :: MacOS
Classifier: Operating System :: MacOS :: MacOS X
Classifier: Programming Language :: Python :: 3
Classifier: Programming Language :: Python :: 3.6
Classifier: Programming Language :: Python :: 3.7
Classifier: Programming Language :: Python :: 3.8
Classifier: Programming Language :: Python :: 3.9
Classifier: Programming Language :: Python :: Implementation :: CPython
Classifier: Topic :: Terminals
Classifier: Topic :: Utilities
Requires-Dist: click (>=7.1.2,<8.0.0)
Requires-Dist: importlib-metadata (>=1.0,<2.0); python_version < "3.8"
Requires-Dist: python-string-utils (>=1.0.0,<2.0.0)
Project-URL: Bug Tracker, https://github.com/joaopalmeiro/vvifi/issues
Project-URL: Repository, https://github.com/joaopalmeiro/vvifi
Project-URL: Twitter, https://twitter.com/joaompalmeiro
